{
  "cache": {
    "sector_CDNS": {
      "data": {
        "sector": "SemiConductor",
        "isleverage": false
      },
      "timestamp": 1756070958.3606095,
      "data_type": "sector"
    },
    "sector_SMTC": {
      "data": {
        "sector": "SemiConductor",
        "isleverage": false
      },
      "timestamp": 1756070958.3634515,
      "data_type": "sector"
    },
    "sector_NVTS": {
      "data": {
        "sector": "SemiConductor",
        "isleverage": false
      },
      "timestamp": 1756070958.3654733,
      "data_type": "sector"
    },
    "sector_SMCX": {
      "data": {
        "sector": "SemiConductor",
        "isleverage": true
      },
      "timestamp": 1756070958.3682184,
      "data_type": "sector"
    },
    "sector_AMDL": {
      "data": {
        "sector": "SemiConductor",
        "isleverage": true
      },
      "timestamp": 1756070958.3704443,
      "data_type": "sector"
    },
    "sector_MVLL": {
      "data": {
        "sector": "SemiConductor",
        "isleverage": true
      },
      "timestamp": 1756070958.372436,
      "data_type": "sector"
    },
    "sector_ARMU": {
      "data": {
        "sector": "SemiConductor",
        "isleverage": true
      },
      "timestamp": 1756070958.37429,
      "data_type": "sector"
    },
    "sector_NAIL": {
      "data": {
        "sector": "Real Estate",
        "isleverage": false
      },
      "timestamp": 1756070958.3760896,
      "data_type": "sector"
    },
    "sector_OPEN": {
      "data": {
        "sector": "Real Estate",
        "isleverage": false
      },
      "timestamp": 1756070958.3779962,
      "data_type": "sector"
    },
    "sector_FNMA": {
      "data": {
        "sector": "Real Estate",
        "isleverage": false
      },
      "timestamp": 1756070958.3803253,
      "data_type": "sector"
    },
    "sector_FMCC": {
      "data": {
        "sector": "Real Estate",
        "isleverage": false
      },
      "timestamp": 1756070958.3823805,
      "data_type": "sector"
    },
    "sector_RKT": {
      "data": {
        "sector": "Real Estate",
        "isleverage": false
      },
      "timestamp": 1756070958.3844779,
      "data_type": "sector"
    },
    "sector_COIN": {
      "data": {
        "sector": "Crypto",
        "isleverage": false
      },
      "timestamp": 1756070958.3865356,
      "data_type": "sector"
    },
    "sector_MARA": {
      "data": {
        "sector": "Crypto",
        "isleverage": false
      },
      "timestamp": 1756070958.3905652,
      "data_type": "sector"
    },
    "sector_RIOT": {
      "data": {
        "sector": "Crypto",
        "isleverage": false
      },
      "timestamp": 1756070958.3925676,
      "data_type": "sector"
    },
    "sector_SOL-USD": {
      "data": {
        "sector": "Crypto",
        "isleverage": false
      },
      "timestamp": 1756070958.394479,
      "data_type": "sector"
    },
    "sector_BTC-USD": {
      "data": {
        "sector": "Crypto",
        "isleverage": false
      },
      "timestamp": 1756070958.3968194,
      "data_type": "sector"
    },
    "sector_ETH-USD": {
      "data": {
        "sector": "Crypto",
        "isleverage": false
      },
      "timestamp": 1756070958.3989966,
      "data_type": "sector"
    },
    "sector_CRCL": {
      "data": {
        "sector": "Crypto",
        "isleverage": false
      },
      "timestamp": 1756070958.401087,
      "data_type": "sector"
    },
    "sector_CONL": {
      "data": {
        "sector": "Crypto",
        "isleverage": true
      },
      "timestamp": 1756070958.403005,
      "data_type": "sector"
    },
    "sector_COIG": {
      "data": {
        "sector": "Crypto",
        "isleverage": true
      },
      "timestamp": 1756070958.4049668,
      "data_type": "sector"
    },
    "sector_MRAL": {
      "data": {
        "sector": "Crypto",
        "isleverage": true
      },
      "timestamp": 1756070958.406922,
      "data_type": "sector"
    },
    "sector_RIOX": {
      "data": {
        "sector": "Crypto",
        "isleverage": true
      },
      "timestamp": 1756070958.4088733,
      "data_type": "sector"
    },
    "sector_MSTX": {
      "data": {
        "sector": "Crypto",
        "isleverage": true
      },
      "timestamp": 1756070958.4108114,
      "data_type": "sector"
    },
    "sector_SOLT": {
      "data": {
        "sector": "Crypto",
        "isleverage": true
      },
      "timestamp": 1756070958.4128413,
      "data_type": "sector"
    },
    "sector_BITU": {
      "data": {
        "sector": "Crypto",
        "isleverage": true
      },
      "timestamp": 1756070958.4148705,
      "data_type": "sector"
    },
    "sector_ETHU": {
      "data": {
        "sector": "Crypto",
        "isleverage": true
      },
      "timestamp": 1756070958.4169228,
      "data_type": "sector"
    },
    "sector_SNOW": {
      "data": {
        "sector": "Security/Software Product",
        "isleverage": false
      },
      "timestamp": 1756070958.4189432,
      "data_type": "sector"
    },
    "sector_PANW": {
      "data": {
        "sector": "Security/Software Product",
        "isleverage": false
      },
      "timestamp": 1756070958.420844,
      "data_type": "sector"
    },
    "sector_CRWD": {
      "data": {
        "sector": "Security/Software Product",
        "isleverage": false
      },
      "timestamp": 1756070958.4227653,
      "data_type": "sector"
    },
    "sector_CRM": {
      "data": {
        "sector": "Security/Software Product",
        "isleverage": false
      },
      "timestamp": 1756070958.4248092,
      "data_type": "sector"
    },
    "sector_MDB": {
      "data": {
        "sector": "Security/Software Product",
        "isleverage": false
      },
      "timestamp": 1756070958.4267805,
      "data_type": "sector"
    },
    "sector_FTNT": {
      "data": {
        "sector": "Security/Software Product",
        "isleverage": false
      },
      "timestamp": 1756070958.429002,
      "data_type": "sector"
    },
    "sector_ZS": {
      "data": {
        "sector": "Security/Software Product",
        "isleverage": false
      },
      "timestamp": 1756070958.431102,
      "data_type": "sector"
    },
    "sector_OKTA": {
      "data": {
        "sector": "Security/Software Product",
        "isleverage": false
      },
      "timestamp": 1756070958.4332929,
      "data_type": "sector"
    },
    "sector_SNOU": {
      "data": {
        "sector": "Security/Software Product",
        "isleverage": true
      },
      "timestamp": 1756070958.435166,
      "data_type": "sector"
    },
    "sector_PANG": {
      "data": {
        "sector": "Security/Software Product",
        "isleverage": true
      },
      "timestamp": 1756070958.437053,
      "data_type": "sector"
    },
    "sector_CRWL": {
      "data": {
        "sector": "Security/Software Product",
        "isleverage": true
      },
      "timestamp": 1756070958.4389987,
      "data_type": "sector"
    },
    "sector_CRMG": {
      "data": {
        "sector": "Security/Software Product",
        "isleverage": true
      },
      "timestamp": 1756070958.4409604,
      "data_type": "sector"
    },
    "sector_HOOD": {
      "data": {
        "sector": "Finance",
        "isleverage": false
      },
      "timestamp": 1756070958.4430103,
      "data_type": "sector"
    },
    "sector_UPST": {
      "data": {
        "sector": "Finance",
        "isleverage": false
      },
      "timestamp": 1756070958.4453607,
      "data_type": "sector"
    },
    "sector_SOFX": {
      "data": {
        "sector": "Finance",
        "isleverage": true
      },
      "timestamp": 1756070958.447832,
      "data_type": "sector"
    },
    "sector_ROBN": {
      "data": {
        "sector": "Finance",
        "isleverage": true
      },
      "timestamp": 1756070958.4500532,
      "data_type": "sector"
    },
    "sector_HOOX": {
      "data": {
        "sector": "Finance",
        "isleverage": true
      },
      "timestamp": 1756070958.4521532,
      "data_type": "sector"
    },
    "sector_UPSX": {
      "data": {
        "sector": "Finance",
        "isleverage": true
      },
      "timestamp": 1756070958.4540544,
      "data_type": "sector"
    },
    "sector_PLTR": {
      "data": {
        "sector": "AI Service",
        "isleverage": false
      },
      "timestamp": 1756070958.45605,
      "data_type": "sector"
    },
    "sector_SOUN": {
      "data": {
        "sector": "AI Service",
        "isleverage": false
      },
      "timestamp": 1756070958.4580982,
      "data_type": "sector"
    },
    "sector_VRTL": {
      "data": {
        "sector": "AI Service",
        "isleverage": true
      },
      "timestamp": 1756070958.460138,
      "data_type": "sector"
    },
    "sector_BBAI": {
      "data": {
        "sector": "AI Service",
        "isleverage": false
      },
      "timestamp": 1756070958.4621017,
      "data_type": "sector"
    },
    "sector_CRWV": {
      "data": {
        "sector": "AI Service",
        "isleverage": false
      },
      "timestamp": 1756070958.4660833,
      "data_type": "sector"
    },
    "sector_GRRR": {
      "data": {
        "sector": "AI Service",
        "isleverage": false
      },
      "timestamp": 1756070958.4681041,
      "data_type": "sector"
    },
    "sector_AI": {
      "data": {
        "sector": "AI Service",
        "isleverage": false
      },
      "timestamp": 1756070958.470179,
      "data_type": "sector"
    },
    "sector_NBIS": {
      "data": {
        "sector": "AI Service",
        "isleverage": false
      },
      "timestamp": 1756070958.4721956,
      "data_type": "sector"
    },
    "sector_PLTU": {
      "data": {
        "sector": "AI Service",
        "isleverage": true
      },
      "timestamp": 1756070958.47418,
      "data_type": "sector"
    },
    "sector_SOUX": {
      "data": {
        "sector": "AI Service",
        "isleverage": true
      },
      "timestamp": 1756070958.4761622,
      "data_type": "sector"
    },
    "sector_META": {
      "data": {
        "sector": "Mega Stocks",
        "isleverage": false
      },
      "timestamp": 1756070958.478277,
      "data_type": "sector"
    },
    "sector_AMZN": {
      "data": {
        "sector": "Mega Stocks",
        "isleverage": false
      },
      "timestamp": 1756070958.480226,
      "data_type": "sector"
    },
    "sector_TSLA": {
      "data": {
        "sector": "Mega Stocks",
        "isleverage": false
      },
      "timestamp": 1756070958.4821422,
      "data_type": "sector"
    },
    "sector_METU": {
      "data": {
        "sector": "Mega Stocks",
        "isleverage": true
      },
      "timestamp": 1756070958.4841907,
      "data_type": "sector"
    },
    "sector_AMZU": {
      "data": {
        "sector": "Mega Stocks",
        "isleverage": true
      },
      "timestamp": 1756070958.486193,
      "data_type": "sector"
    },
    "sector_TSLL": {
      "data": {
        "sector": "Mega Stocks",
        "isleverage": true
      },
      "timestamp": 1756070958.488166,
      "data_type": "sector"
    },
    "sector_NVDL": {
      "data": {
        "sector": "Mega Stocks",
        "isleverage": true
      },
      "timestamp": 1756070958.490277,
      "data_type": "sector"
    },
    "sector_NFXL": {
      "data": {
        "sector": "Mega Stocks",
        "isleverage": true
      },
      "timestamp": 1756070958.4923494,
      "data_type": "sector"
    },
    "sector_AAPU": {
      "data": {
        "sector": "Mega Stocks",
        "isleverage": true
      },
      "timestamp": 1756070958.4946527,
      "data_type": "sector"
    },
    "sector_GGLL": {
      "data": {
        "sector": "Mega Stocks",
        "isleverage": true
      },
      "timestamp": 1756070958.4967282,
      "data_type": "sector"
    },
    "sector_MSFU": {
      "data": {
        "sector": "Mega Stocks",
        "isleverage": true
      },
      "timestamp": 1756070958.498964,
      "data_type": "sector"
    },
    "sector_TQQQ": {
      "data": {
        "sector": "Mega Stocks",
        "isleverage": true
      },
      "timestamp": 1756070958.5012088,
      "data_type": "sector"
    },
    "sector_OKLO": {
      "data": {
        "sector": "Energy",
        "isleverage": false
      },
      "timestamp": 1756070958.503226,
      "data_type": "sector"
    },
    "sector_NNE": {
      "data": {
        "sector": "Energy",
        "isleverage": false
      },
      "timestamp": 1756070958.505233,
      "data_type": "sector"
    },
    "sector_SMR": {
      "data": {
        "sector": "Energy",
        "isleverage": false
      },
      "timestamp": 1756070958.5072381,
      "data_type": "sector"
    },
    "sector_UUUU": {
      "data": {
        "sector": "Energy",
        "isleverage": false
      },
      "timestamp": 1756070958.5092676,
      "data_type": "sector"
    },
    "sector_NXE": {
      "data": {
        "sector": "Energy",
        "isleverage": false
      },
      "timestamp": 1756070958.5112858,
      "data_type": "sector"
    },
    "sector_OKLL": {
      "data": {
        "sector": "Energy",
        "isleverage": true
      },
      "timestamp": 1756070958.5135586,
      "data_type": "sector"
    },
    "sector_TEM": {
      "data": {
        "sector": "Healthcare",
        "isleverage": false
      },
      "timestamp": 1756070958.5156026,
      "data_type": "sector"
    },
    "sector_NVO": {
      "data": {
        "sector": "Healthcare",
        "isleverage": false
      },
      "timestamp": 1756070958.5176842,
      "data_type": "sector"
    },
    "sector_HIMZ": {
      "data": {
        "sector": "Healthcare",
        "isleverage": true
      },
      "timestamp": 1756070958.5196333,
      "data_type": "sector"
    },
    "sector_TEMT": {
      "data": {
        "sector": "Healthcare",
        "isleverage": true
      },
      "timestamp": 1756070958.521665,
      "data_type": "sector"
    },
    "sector_NVOX": {
      "data": {
        "sector": "Healthcare",
        "isleverage": true
      },
      "timestamp": 1756070958.5236578,
      "data_type": "sector"
    },
    "sector_RDTL": {
      "data": {
        "sector": "Others",
        "isleverage": false
      },
      "timestamp": 1756070958.5257387,
      "data_type": "sector"
    },
    "sector_APPS": {
      "data": {
        "sector": "Others",
        "isleverage": false
      },
      "timestamp": 1756070958.527614,
      "data_type": "sector"
    },
    "sector_RBLU": {
      "data": {
        "sector": "Others",
        "isleverage": false
      },
      "timestamp": 1756070958.5298479,
      "data_type": "sector"
    },
    "sector_CVNX": {
      "data": {
        "sector": "Others",
        "isleverage": false
      },
      "timestamp": 1756070958.5318823,
      "data_type": "sector"
    },
    "sector_SERV": {
      "data": {
        "sector": "Others",
        "isleverage": false
      },
      "timestamp": 1756070958.533951,
      "data_type": "sector"
    },
    "sector_ARQQ": {
      "data": {
        "sector": "Quantum",
        "isleverage": false
      },
      "timestamp": 1756070958.5360236,
      "data_type": "sector"
    },
    "sector_IONQ": {
      "data": {
        "sector": "Quantum",
        "isleverage": false
      },
      "timestamp": 1756070958.538043,
      "data_type": "sector"
    },
    "sector_AIRE": {
      "data": {
        "sector": "Real Estate",
        "isleverage": false
      },
      "timestamp": 1756070958.539958,
      "data_type": "sector"
    },
    "sector_APLD": {
      "data": {
        "sector": "AI Service",
        "isleverage": false
      },
      "timestamp": 1756070958.541949,
      "data_type": "sector"
    },
    "sector_SOFI": {
      "data": {
        "sector": "Finance",
        "isleverage": false
      },
      "timestamp": 1756070958.544054,
      "data_type": "sector"
    },
    "sector_NFLX": {
      "data": {
        "sector": "Mega Stocks",
        "isleverage": false
      },
      "timestamp": 1756070958.546177,
      "data_type": "sector"
    },
    "sector_AAPL": {
      "data": {
        "sector": "Mega Stocks",
        "isleverage": false
      },
      "timestamp": 1756070958.5483353,
      "data_type": "sector"
    },
    "sector_GOOG": {
      "data": {
        "sector": "Mega Stocks",
        "isleverage": false
      },
      "timestamp": 1756070958.5503504,
      "data_type": "sector"
    },
    "sector_NVDA": {
      "data": {
        "sector": "Mega Stocks",
        "isleverage": false
      },
      "timestamp": 1756070958.5524309,
      "data_type": "sector"
    },
    "sector_MSFT": {
      "data": {
        "sector": "Mega Stocks",
        "isleverage": false
      },
      "timestamp": 1756070958.5545182,
      "data_type": "sector"
    },
    "sector_QQQ": {
      "data": {
        "sector": "Mega Stocks",
        "isleverage": false
      },
      "timestamp": 1756070958.5566425,
      "data_type": "sector"
    },
    "sector_SMU": {
      "data": {
        "sector": "Energy",
        "isleverage": true
      },
      "timestamp": 1756070958.5586421,
      "data_type": "sector"
    },
    "sector_VERI": {
      "data": {
        "sector": "AI Service",
        "isleverage": false
      },
      "timestamp": 1756070958.5607283,
      "data_type": "sector"
    },
    "sector_WULF": {
      "data": {
        "sector": "Crypto",
        "isleverage": false
      },
      "timestamp": 1756070958.5630558,
      "data_type": "sector"
    },
    "sector_HIMS": {
      "data": {
        "sector": "Health & Pharma",
        "isleverage": false
      },
      "timestamp": 1756070958.5653257,
      "data_type": "sector"
    },
    "sector_UNH": {
      "data": {
        "sector": "Health & Pharma",
        "isleverage": false
      },
      "timestamp": 1756070958.5674453,
      "data_type": "sector"
    },
    "sector_UNHG": {
      "data": {
        "sector": "Health & Pharma",
        "isleverage": true
      },
      "timestamp": 1756070958.569342,
      "data_type": "sector"
    }
  },
  "metadata": {
    "sector_CDNS": {
      "created_at": 1756070958.3606102,
      "data_type": "sector",
      "size": 48
    },
    "sector_SMTC": {
      "created_at": 1756070958.363452,
      "data_type": "sector",
      "size": 48
    },
    "sector_NVTS": {
      "created_at": 1756070958.365474,
      "data_type": "sector",
      "size": 48
    },
    "sector_SMCX": {
      "created_at": 1756070958.368219,
      "data_type": "sector",
      "size": 47
    },
    "sector_AMDL": {
      "created_at": 1756070958.3704448,
      "data_type": "sector",
      "size": 47
    },
    "sector_MVLL": {
      "created_at": 1756070958.3724365,
      "data_type": "sector",
      "size": 47
    },
    "sector_ARMU": {
      "created_at": 1756070958.3742905,
      "data_type": "sector",
      "size": 47
    },
    "sector_NAIL": {
      "created_at": 1756070958.37609,
      "data_type": "sector",
      "size": 46
    },
    "sector_OPEN": {
      "created_at": 1756070958.3779967,
      "data_type": "sector",
      "size": 46
    },
    "sector_FNMA": {
      "created_at": 1756070958.3803265,
      "data_type": "sector",
      "size": 46
    },
    "sector_FMCC": {
      "created_at": 1756070958.3823812,
      "data_type": "sector",
      "size": 46
    },
    "sector_RKT": {
      "created_at": 1756070958.3844786,
      "data_type": "sector",
      "size": 46
    },
    "sector_COIN": {
      "created_at": 1756070958.3865373,
      "data_type": "sector",
      "size": 41
    },
    "sector_MARA": {
      "created_at": 1756070958.3905804,
      "data_type": "sector",
      "size": 41
    },
    "sector_RIOT": {
      "created_at": 1756070958.3925683,
      "data_type": "sector",
      "size": 41
    },
    "sector_SOL-USD": {
      "created_at": 1756070958.3944802,
      "data_type": "sector",
      "size": 41
    },
    "sector_BTC-USD": {
      "created_at": 1756070958.3968205,
      "data_type": "sector",
      "size": 41
    },
    "sector_ETH-USD": {
      "created_at": 1756070958.3989973,
      "data_type": "sector",
      "size": 41
    },
    "sector_CRCL": {
      "created_at": 1756070958.4010875,
      "data_type": "sector",
      "size": 41
    },
    "sector_CONL": {
      "created_at": 1756070958.4030054,
      "data_type": "sector",
      "size": 40
    },
    "sector_COIG": {
      "created_at": 1756070958.4049673,
      "data_type": "sector",
      "size": 40
    },
    "sector_MRAL": {
      "created_at": 1756070958.4069226,
      "data_type": "sector",
      "size": 40
    },
    "sector_RIOX": {
      "created_at": 1756070958.4088738,
      "data_type": "sector",
      "size": 40
    },
    "sector_MSTX": {
      "created_at": 1756070958.410812,
      "data_type": "sector",
      "size": 40
    },
    "sector_SOLT": {
      "created_at": 1756070958.4128423,
      "data_type": "sector",
      "size": 40
    },
    "sector_BITU": {
      "created_at": 1756070958.4148707,
      "data_type": "sector",
      "size": 40
    },
    "sector_ETHU": {
      "created_at": 1756070958.4169238,
      "data_type": "sector",
      "size": 40
    },
    "sector_SNOW": {
      "created_at": 1756070958.418944,
      "data_type": "sector",
      "size": 60
    },
    "sector_PANW": {
      "created_at": 1756070958.4208446,
      "data_type": "sector",
      "size": 60
    },
    "sector_CRWD": {
      "created_at": 1756070958.422766,
      "data_type": "sector",
      "size": 60
    },
    "sector_CRM": {
      "created_at": 1756070958.42481,
      "data_type": "sector",
      "size": 60
    },
    "sector_MDB": {
      "created_at": 1756070958.4267812,
      "data_type": "sector",
      "size": 60
    },
    "sector_FTNT": {
      "created_at": 1756070958.429003,
      "data_type": "sector",
      "size": 60
    },
    "sector_ZS": {
      "created_at": 1756070958.4311028,
      "data_type": "sector",
      "size": 60
    },
    "sector_OKTA": {
      "created_at": 1756070958.4332936,
      "data_type": "sector",
      "size": 60
    },
    "sector_SNOU": {
      "created_at": 1756070958.4351668,
      "data_type": "sector",
      "size": 59
    },
    "sector_PANG": {
      "created_at": 1756070958.4370537,
      "data_type": "sector",
      "size": 59
    },
    "sector_CRWL": {
      "created_at": 1756070958.4389994,
      "data_type": "sector",
      "size": 59
    },
    "sector_CRMG": {
      "created_at": 1756070958.4409614,
      "data_type": "sector",
      "size": 59
    },
    "sector_HOOD": {
      "created_at": 1756070958.443011,
      "data_type": "sector",
      "size": 42
    },
    "sector_UPST": {
      "created_at": 1756070958.4453614,
      "data_type": "sector",
      "size": 42
    },
    "sector_SOFX": {
      "created_at": 1756070958.447833,
      "data_type": "sector",
      "size": 41
    },
    "sector_ROBN": {
      "created_at": 1756070958.4500537,
      "data_type": "sector",
      "size": 41
    },
    "sector_HOOX": {
      "created_at": 1756070958.452154,
      "data_type": "sector",
      "size": 41
    },
    "sector_UPSX": {
      "created_at": 1756070958.454055,
      "data_type": "sector",
      "size": 41
    },
    "sector_PLTR": {
      "created_at": 1756070958.4560506,
      "data_type": "sector",
      "size": 45
    },
    "sector_SOUN": {
      "created_at": 1756070958.4581015,
      "data_type": "sector",
      "size": 45
    },
    "sector_VRTL": {
      "created_at": 1756070958.4601388,
      "data_type": "sector",
      "size": 44
    },
    "sector_BBAI": {
      "created_at": 1756070958.4621024,
      "data_type": "sector",
      "size": 45
    },
    "sector_CRWV": {
      "created_at": 1756070958.466084,
      "data_type": "sector",
      "size": 45
    },
    "sector_GRRR": {
      "created_at": 1756070958.4681053,
      "data_type": "sector",
      "size": 45
    },
    "sector_AI": {
      "created_at": 1756070958.4701798,
      "data_type": "sector",
      "size": 45
    },
    "sector_NBIS": {
      "created_at": 1756070958.472197,
      "data_type": "sector",
      "size": 45
    },
    "sector_PLTU": {
      "created_at": 1756070958.4741807,
      "data_type": "sector",
      "size": 44
    },
    "sector_SOUX": {
      "created_at": 1756070958.4761631,
      "data_type": "sector",
      "size": 44
    },
    "sector_META": {
      "created_at": 1756070958.4782774,
      "data_type": "sector",
      "size": 46
    },
    "sector_AMZN": {
      "created_at": 1756070958.4802268,
      "data_type": "sector",
      "size": 46
    },
    "sector_TSLA": {
      "created_at": 1756070958.482143,
      "data_type": "sector",
      "size": 46
    },
    "sector_METU": {
      "created_at": 1756070958.4841914,
      "data_type": "sector",
      "size": 45
    },
    "sector_AMZU": {
      "created_at": 1756070958.4861937,
      "data_type": "sector",
      "size": 45
    },
    "sector_TSLL": {
      "created_at": 1756070958.4881668,
      "data_type": "sector",
      "size": 45
    },
    "sector_NVDL": {
      "created_at": 1756070958.490278,
      "data_type": "sector",
      "size": 45
    },
    "sector_NFXL": {
      "created_at": 1756070958.4923506,
      "data_type": "sector",
      "size": 45
    },
    "sector_AAPU": {
      "created_at": 1756070958.4946535,
      "data_type": "sector",
      "size": 45
    },
    "sector_GGLL": {
      "created_at": 1756070958.496729,
      "data_type": "sector",
      "size": 45
    },
    "sector_MSFU": {
      "created_at": 1756070958.4989648,
      "data_type": "sector",
      "size": 45
    },
    "sector_TQQQ": {
      "created_at": 1756070958.5012095,
      "data_type": "sector",
      "size": 45
    },
    "sector_OKLO": {
      "created_at": 1756070958.5032265,
      "data_type": "sector",
      "size": 41
    },
    "sector_NNE": {
      "created_at": 1756070958.505234,
      "data_type": "sector",
      "size": 41
    },
    "sector_SMR": {
      "created_at": 1756070958.5072389,
      "data_type": "sector",
      "size": 41
    },
    "sector_UUUU": {
      "created_at": 1756070958.5092683,
      "data_type": "sector",
      "size": 41
    },
    "sector_NXE": {
      "created_at": 1756070958.5112865,
      "data_type": "sector",
      "size": 41
    },
    "sector_OKLL": {
      "created_at": 1756070958.5135593,
      "data_type": "sector",
      "size": 40
    },
    "sector_TEM": {
      "created_at": 1756070958.5156033,
      "data_type": "sector",
      "size": 45
    },
    "sector_NVO": {
      "created_at": 1756070958.517685,
      "data_type": "sector",
      "size": 45
    },
    "sector_HIMZ": {
      "created_at": 1756070958.519634,
      "data_type": "sector",
      "size": 44
    },
    "sector_TEMT": {
      "created_at": 1756070958.5216656,
      "data_type": "sector",
      "size": 44
    },
    "sector_NVOX": {
      "created_at": 1756070958.5236583,
      "data_type": "sector",
      "size": 44
    },
    "sector_RDTL": {
      "created_at": 1756070958.5257392,
      "data_type": "sector",
      "size": 41
    },
    "sector_APPS": {
      "created_at": 1756070958.527615,
      "data_type": "sector",
      "size": 41
    },
    "sector_RBLU": {
      "created_at": 1756070958.5298488,
      "data_type": "sector",
      "size": 41
    },
    "sector_CVNX": {
      "created_at": 1756070958.531883,
      "data_type": "sector",
      "size": 41
    },
    "sector_SERV": {
      "created_at": 1756070958.5339518,
      "data_type": "sector",
      "size": 41
    },
    "sector_ARQQ": {
      "created_at": 1756070958.5360243,
      "data_type": "sector",
      "size": 42
    },
    "sector_IONQ": {
      "created_at": 1756070958.538044,
      "data_type": "sector",
      "size": 42
    },
    "sector_AIRE": {
      "created_at": 1756070958.5399587,
      "data_type": "sector",
      "size": 46
    },
    "sector_APLD": {
      "created_at": 1756070958.5419497,
      "data_type": "sector",
      "size": 45
    },
    "sector_SOFI": {
      "created_at": 1756070958.5440545,
      "data_type": "sector",
      "size": 42
    },
    "sector_NFLX": {
      "created_at": 1756070958.5461776,
      "data_type": "sector",
      "size": 46
    },
    "sector_AAPL": {
      "created_at": 1756070958.548336,
      "data_type": "sector",
      "size": 46
    },
    "sector_GOOG": {
      "created_at": 1756070958.5503511,
      "data_type": "sector",
      "size": 46
    },
    "sector_NVDA": {
      "created_at": 1756070958.5524316,
      "data_type": "sector",
      "size": 46
    },
    "sector_MSFT": {
      "created_at": 1756070958.5545187,
      "data_type": "sector",
      "size": 46
    },
    "sector_QQQ": {
      "created_at": 1756070958.5566444,
      "data_type": "sector",
      "size": 46
    },
    "sector_SMU": {
      "created_at": 1756070958.5586426,
      "data_type": "sector",
      "size": 40
    },
    "sector_VERI": {
      "created_at": 1756070958.5607302,
      "data_type": "sector",
      "size": 45
    },
    "sector_WULF": {
      "created_at": 1756070958.5630565,
      "data_type": "sector",
      "size": 41
    },
    "sector_HIMS": {
      "created_at": 1756070958.5653265,
      "data_type": "sector",
      "size": 50
    },
    "sector_UNH": {
      "created_at": 1756070958.567446,
      "data_type": "sector",
      "size": 50
    },
    "sector_UNHG": {
      "created_at": 1756070958.5693424,
      "data_type": "sector",
      "size": 49
    }
  },
  "last_updated": "2025-08-24T14:29:18.569346"
}